[
  {
    "BUSINESS_TYPE": "Animal Care Facility", 
    "ACCESS2": 3.701267607737792, 
    "YEAR": 2011, 
    "ACCESS1": 40.98939351074814, 
    "COMMUNITY_AREA": "CALUMET HEIGHTS"
  }, 
  {
    "BUSINESS_TYPE": "Animal Care Facility", 
    "ACCESS2": 182.0332131425854, 
    "YEAR": 2011, 
    "ACCESS1": 267.0691242573378, 
    "COMMUNITY_AREA": "ROGERS PARK"
  }, 
  {
    "BUSINESS_TYPE": "Animal Care Facility", 
    "ACCESS2": 372.29290179342513, 
    "YEAR": 2011, 
    "ACCESS1": 406.7735070224729, 
    "COMMUNITY_AREA": "LINCOLN SQUARE"
  }, 
  {
    "BUSINESS_TYPE": "Animal Care Facility", 
    "ACCESS2": 100.36811688893225, 
    "YEAR": 2011, 
    "ACCESS1": 333.0149916149663, 
    "COMMUNITY_AREA": "NORTH LAWNDALE"
  }, 
  {
    "BUSINESS_TYPE": "Animal Care Facility", 
    "ACCESS2": 14.205476353400007, 
    "YEAR": 2011, 
    "ACCESS1": 118.46456705976904, 
    "COMMUNITY_AREA": "ROSELAND"
  }, 
  {
    "BUSINESS_TYPE": "Animal Care Facility", 
    "ACCESS2": 37.95788334140142, 
    "YEAR": 2011, 
    "ACCESS1": 149.06126524349628, 
    "COMMUNITY_AREA": "CHICAGO LAWN"
  }, 
  {
    "BUSINESS_TYPE": "Animal Care Facility", 
    "ACCESS2": 13.31430023508709, 
    "YEAR": 2011, 
    "ACCESS1": 136.96012943174455, 
    "COMMUNITY_AREA": "SOUTH SHORE"
  }, 
  {
    "BUSINESS_TYPE": "Animal Care Facility", 
    "ACCESS2": 38.598257897885084, 
    "YEAR": 2011, 
    "ACCESS1": 166.91548828915253, 
    "COMMUNITY_AREA": "DOUGLAS"
  }, 
  {
    "BUSINESS_TYPE": "Animal Care Facility", 
    "ACCESS2": 13.942997413426133, 
    "YEAR": 2011, 
    "ACCESS1": 117.46945497880176, 
    "COMMUNITY_AREA": "WOODLAWN"
  }, 
  {
    "BUSINESS_TYPE": "Animal Care Facility", 
    "ACCESS2": 19.188892765933517, 
    "YEAR": 2011, 
    "ACCESS1": 138.32338260045657, 
    "COMMUNITY_AREA": "HYDE PARK"
  }, 
  {
    "BUSINESS_TYPE": "Animal Care Facility", 
    "ACCESS2": 21.881306823201914, 
    "YEAR": 2011, 
    "ACCESS1": 98.53623885892293, 
    "COMMUNITY_AREA": "FOREST GLEN"
  }, 
  {
    "BUSINESS_TYPE": "Animal Care Facility", 
    "ACCESS2": 3.146105924078175, 
    "YEAR": 2011, 
    "ACCESS1": 13.833570871136688, 
    "COMMUNITY_AREA": "HEGEWISCH"
  }, 
  {
    "BUSINESS_TYPE": "Animal Care Facility", 
    "ACCESS2": 6.7932016938040025, 
    "YEAR": 2011, 
    "ACCESS1": 79.97983327292698, 
    "COMMUNITY_AREA": "SOUTH CHICAGO"
  }, 
  {
    "BUSINESS_TYPE": "Animal Care Facility", 
    "ACCESS2": 35.67757806733667, 
    "YEAR": 2011, 
    "ACCESS1": 81.46040076533188, 
    "COMMUNITY_AREA": "ARCHER HEIGHTS"
  }, 
  {
    "BUSINESS_TYPE": "Animal Care Facility", 
    "ACCESS2": 25.991902135185512, 
    "YEAR": 2011, 
    "ACCESS1": 75.0498511798134, 
    "COMMUNITY_AREA": "BEVERLY"
  }, 
  {
    "BUSINESS_TYPE": "Animal Care Facility", 
    "ACCESS2": 281.3956336642011, 
    "YEAR": 2011, 
    "ACCESS1": 412.56829528165855, 
    "COMMUNITY_AREA": "UPTOWN"
  }, 
  {
    "BUSINESS_TYPE": "Animal Care Facility", 
    "ACCESS2": 440.1055876352116, 
    "YEAR": 2011, 
    "ACCESS1": 400.27533663377653, 
    "COMMUNITY_AREA": "AVONDALE"
  }, 
  {
    "BUSINESS_TYPE": "Animal Care Facility", 
    "ACCESS2": 1.6671911541452074, 
    "YEAR": 2011, 
    "ACCESS1": 17.500176291331726, 
    "COMMUNITY_AREA": "AVALON PARK"
  }, 
  {
    "BUSINESS_TYPE": "Animal Care Facility", 
    "ACCESS2": 0.8196053330489117, 
    "YEAR": 2011, 
    "ACCESS1": 8.470501017242992, 
    "COMMUNITY_AREA": "BURNSIDE"
  }, 
  {
    "BUSINESS_TYPE": "Animal Care Facility", 
    "ACCESS2": 84.49609614976833, 
    "YEAR": 2011, 
    "ACCESS1": 260.1761249558609, 
    "COMMUNITY_AREA": "LOWER WEST SIDE"
  }, 
  {
    "BUSINESS_TYPE": "Animal Care Facility", 
    "ACCESS2": 273.5047467948058, 
    "YEAR": 2011, 
    "ACCESS1": 365.0699754557732, 
    "COMMUNITY_AREA": "SOUTH LAWNDALE"
  }, 
  {
    "BUSINESS_TYPE": "Animal Care Facility", 
    "ACCESS2": 25.50237538479052, 
    "YEAR": 2011, 
    "ACCESS1": 158.59611346446485, 
    "COMMUNITY_AREA": "DUNNING"
  }, 
  {
    "BUSINESS_TYPE": "Animal Care Facility", 
    "ACCESS2": 117.57123745906844, 
    "YEAR": 2011, 
    "ACCESS1": 301.64281047843076, 
    "COMMUNITY_AREA": "ALBANY PARK"
  }, 
  {
    "BUSINESS_TYPE": "Animal Care Facility", 
    "ACCESS2": 2.268450367197295, 
    "YEAR": 2011, 
    "ACCESS1": 23.387542783550792, 
    "COMMUNITY_AREA": "PULLMAN"
  }, 
  {
    "BUSINESS_TYPE": "Animal Care Facility", 
    "ACCESS2": 57.37816211440506, 
    "YEAR": 2011, 
    "ACCESS1": 133.03389597945946, 
    "COMMUNITY_AREA": "LOOP"
  }, 
  {
    "BUSINESS_TYPE": "Animal Care Facility", 
    "ACCESS2": 42.95954240864882, 
    "YEAR": 2011, 
    "ACCESS1": 186.55199912862145, 
    "COMMUNITY_AREA": "BRIDGEPORT"
  }, 
  {
    "BUSINESS_TYPE": "Animal Care Facility", 
    "ACCESS2": 24.514586878006263, 
    "YEAR": 2011, 
    "ACCESS1": 158.27721001063745, 
    "COMMUNITY_AREA": "AUBURN GRESHAM"
  }, 
  {
    "BUSINESS_TYPE": "Animal Care Facility", 
    "ACCESS2": 1851.2188884282598, 
    "YEAR": 2011, 
    "ACCESS1": 1552.9069246474871, 
    "COMMUNITY_AREA": "LAKE VIEW"
  }, 
  {
    "BUSINESS_TYPE": "Animal Care Facility", 
    "ACCESS2": 327.62033533119904, 
    "YEAR": 2011, 
    "ACCESS1": 500.0276114697292, 
    "COMMUNITY_AREA": "HUMBOLDT PARK"
  }, 
  {
    "BUSINESS_TYPE": "Animal Care Facility", 
    "ACCESS2": 84.23799400708863, 
    "YEAR": 2011, 
    "ACCESS1": 238.98503917477458, 
    "COMMUNITY_AREA": "WEST GARFIELD PARK"
  }, 
  {
    "BUSINESS_TYPE": "Animal Care Facility", 
    "ACCESS2": 31.00619457795508, 
    "YEAR": 2011, 
    "ACCESS1": 111.87768132051755, 
    "COMMUNITY_AREA": "NORWOOD PARK"
  }, 
  {
    "BUSINESS_TYPE": "Animal Care Facility", 
    "ACCESS2": 360.6861032436873, 
    "YEAR": 2011, 
    "ACCESS1": 381.2808403708204, 
    "COMMUNITY_AREA": "EAST GARFIELD PARK"
  }, 
  {
    "BUSINESS_TYPE": "Animal Care Facility", 
    "ACCESS2": 1096.121902057856, 
    "YEAR": 2011, 
    "ACCESS1": 1172.3664012070653, 
    "COMMUNITY_AREA": "LOGAN SQUARE"
  }, 
  {
    "BUSINESS_TYPE": "Animal Care Facility", 
    "ACCESS2": 95.5957593536569, 
    "YEAR": 2011, 
    "ACCESS1": 287.4016394334547, 
    "COMMUNITY_AREA": "PORTAGE PARK"
  }, 
  {
    "BUSINESS_TYPE": "Animal Care Facility", 
    "ACCESS2": 2.5413977791422444, 
    "YEAR": 2011, 
    "ACCESS1": 29.481282229906007, 
    "COMMUNITY_AREA": "SOUTH DEERING"
  }, 
  {
    "BUSINESS_TYPE": "Animal Care Facility", 
    "ACCESS2": 1586.1583376212018, 
    "YEAR": 2011, 
    "ACCESS1": 991.3163309896906, 
    "COMMUNITY_AREA": "LINCOLN PARK"
  }, 
  {
    "BUSINESS_TYPE": "Animal Care Facility", 
    "ACCESS2": 20.36823687538652, 
    "YEAR": 2011, 
    "ACCESS1": 101.07406147077886, 
    "COMMUNITY_AREA": "JEFFERSON PARK"
  }, 
  {
    "BUSINESS_TYPE": "Animal Care Facility", 
    "ACCESS2": 415.0745628666069, 
    "YEAR": 2011, 
    "ACCESS1": 504.11621410576646, 
    "COMMUNITY_AREA": "EDGEWATER"
  }, 
  {
    "BUSINESS_TYPE": "Animal Care Facility", 
    "ACCESS2": 9.765246178941773, 
    "YEAR": 2011, 
    "ACCESS1": 91.63023318131889, 
    "COMMUNITY_AREA": "CHATHAM"
  }, 
  {
    "BUSINESS_TYPE": "Animal Care Facility", 
    "ACCESS2": 81.33046333120984, 
    "YEAR": 2011, 
    "ACCESS1": 99.80475568258909, 
    "COMMUNITY_AREA": "WEST LAWN"
  }, 
  {
    "BUSINESS_TYPE": "Animal Care Facility", 
    "ACCESS2": 261.2751698127537, 
    "YEAR": 2011, 
    "ACCESS1": 362.4128970965881, 
    "COMMUNITY_AREA": "WEST RIDGE"
  }, 
  {
    "BUSINESS_TYPE": "Animal Care Facility", 
    "ACCESS2": 1379.8449091611365, 
    "YEAR": 2011, 
    "ACCESS1": 796.482354569, 
    "COMMUNITY_AREA": "NEAR WEST SIDE"
  }, 
  {
    "BUSINESS_TYPE": "Animal Care Facility", 
    "ACCESS2": 17.733275516891492, 
    "YEAR": 2011, 
    "ACCESS1": 129.61131113012482, 
    "COMMUNITY_AREA": "ENGLEWOOD"
  }, 
  {
    "BUSINESS_TYPE": "Animal Care Facility", 
    "ACCESS2": 1182.5828374556756, 
    "YEAR": 2011, 
    "ACCESS1": 747.8382339065361, 
    "COMMUNITY_AREA": "NORTH CENTER"
  }, 
  {
    "BUSINESS_TYPE": "Animal Care Facility", 
    "ACCESS2": 10.52103035854797, 
    "YEAR": 2011, 
    "ACCESS1": 72.28792651197394, 
    "COMMUNITY_AREA": "WASHINGTON PARK"
  }, 
  {
    "BUSINESS_TYPE": "Animal Care Facility", 
    "ACCESS2": 33.40234208822753, 
    "YEAR": 2011, 
    "ACCESS1": 65.19571626660334, 
    "COMMUNITY_AREA": "NEAR SOUTH SIDE"
  }, 
  {
    "BUSINESS_TYPE": "Animal Care Facility", 
    "ACCESS2": 9.509853016801445, 
    "YEAR": 2011, 
    "ACCESS1": 86.99441979354916, 
    "COMMUNITY_AREA": "OHARE"
  }, 
  {
    "BUSINESS_TYPE": "Animal Care Facility", 
    "ACCESS2": 12.052700469427071, 
    "YEAR": 2011, 
    "ACCESS1": 62.97182704507459, 
    "COMMUNITY_AREA": "WEST PULLMAN"
  }, 
  {
    "BUSINESS_TYPE": "Animal Care Facility", 
    "ACCESS2": 507.1840791695036, 
    "YEAR": 2011, 
    "ACCESS1": 682.7324912741299, 
    "COMMUNITY_AREA": "NEAR NORTH SIDE"
  }, 
  {
    "BUSINESS_TYPE": "Animal Care Facility", 
    "ACCESS2": 34.23100902788101, 
    "YEAR": 2011, 
    "ACCESS1": 45.617170245081994, 
    "COMMUNITY_AREA": "MOUNT GREENWOOD"
  }, 
  {
    "BUSINESS_TYPE": "Animal Care Facility", 
    "ACCESS2": 5.708213432424553, 
    "YEAR": 2011, 
    "ACCESS1": 28.727216040976778, 
    "COMMUNITY_AREA": "FULLER PARK"
  }, 
  {
    "BUSINESS_TYPE": "Animal Care Facility", 
    "ACCESS2": 5.04568454815706, 
    "YEAR": 2011, 
    "ACCESS1": 30.478651739045773, 
    "COMMUNITY_AREA": "MONTCLARE"
  }, 
  {
    "BUSINESS_TYPE": "Animal Care Facility", 
    "ACCESS2": 503.06966848841233, 
    "YEAR": 2011, 
    "ACCESS1": 498.99232652571084, 
    "COMMUNITY_AREA": "IRVING PARK"
  }, 
  {
    "BUSINESS_TYPE": "Animal Care Facility", 
    "ACCESS2": 104.06780152507002, 
    "YEAR": 2011, 
    "ACCESS1": 227.99989793271445, 
    "COMMUNITY_AREA": "GRAND BOULEVARD"
  }, 
  {
    "BUSINESS_TYPE": "Animal Care Facility", 
    "ACCESS2": 1.2538060572017218, 
    "YEAR": 2011, 
    "ACCESS1": 13.462161265392094, 
    "COMMUNITY_AREA": "RIVERDALE"
  }, 
  {
    "BUSINESS_TYPE": "Animal Care Facility", 
    "ACCESS2": 199.31038254566337, 
    "YEAR": 2011, 
    "ACCESS1": 189.89060384560952, 
    "COMMUNITY_AREA": "HERMOSA"
  }, 
  {
    "BUSINESS_TYPE": "Animal Care Facility", 
    "ACCESS2": 27.570243111880917, 
    "YEAR": 2011, 
    "ACCESS1": 91.24152389041278, 
    "COMMUNITY_AREA": "NORTH PARK"
  }, 
  {
    "BUSINESS_TYPE": "Animal Care Facility", 
    "ACCESS2": 135.34414405834303, 
    "YEAR": 2011, 
    "ACCESS1": 371.84339670387556, 
    "COMMUNITY_AREA": "BELMONT CRAGIN"
  }, 
  {
    "BUSINESS_TYPE": "Animal Care Facility", 
    "ACCESS2": 24.127794885324114, 
    "YEAR": 2011, 
    "ACCESS1": 93.28224856082225, 
    "COMMUNITY_AREA": "ARMOUR SQUARE"
  }, 
  {
    "BUSINESS_TYPE": "Animal Care Facility", 
    "ACCESS2": 35.63013494055341, 
    "YEAR": 2011, 
    "ACCESS1": 234.74886880220137, 
    "COMMUNITY_AREA": "WEST ENGLEWOOD"
  }, 
  {
    "BUSINESS_TYPE": "Animal Care Facility", 
    "ACCESS2": 18.637981698415533, 
    "YEAR": 2011, 
    "ACCESS1": 90.58297445505562, 
    "COMMUNITY_AREA": "KENWOOD"
  }, 
  {
    "BUSINESS_TYPE": "Animal Care Facility", 
    "ACCESS2": 99.58644887494152, 
    "YEAR": 2011, 
    "ACCESS1": 101.53964872316158, 
    "COMMUNITY_AREA": "CLEARING"
  }, 
  {
    "BUSINESS_TYPE": "Animal Care Facility", 
    "ACCESS2": 18.519359264692834, 
    "YEAR": 2011, 
    "ACCESS1": 79.39591644498475, 
    "COMMUNITY_AREA": "WASHINGTON HEIGHTS"
  }, 
  {
    "BUSINESS_TYPE": "Animal Care Facility", 
    "ACCESS2": 3.3202634906454613, 
    "YEAR": 2011, 
    "ACCESS1": 41.33705624050894, 
    "COMMUNITY_AREA": "EAST SIDE"
  }, 
  {
    "BUSINESS_TYPE": "Animal Care Facility", 
    "ACCESS2": 74.27942946502164, 
    "YEAR": 2011, 
    "ACCESS1": 161.5265157785431, 
    "COMMUNITY_AREA": "GARFIELD RIDGE"
  }, 
  {
    "BUSINESS_TYPE": "Animal Care Facility", 
    "ACCESS2": 89.65906614601548, 
    "YEAR": 2011, 
    "ACCESS1": 100.80961521750349, 
    "COMMUNITY_AREA": "ASHBURN"
  }, 
  {
    "BUSINESS_TYPE": "Animal Care Facility", 
    "ACCESS2": 47.77166761854422, 
    "YEAR": 2011, 
    "ACCESS1": 71.09536431575805, 
    "COMMUNITY_AREA": "WEST ELSDON"
  }, 
  {
    "BUSINESS_TYPE": "Animal Care Facility", 
    "ACCESS2": 20.036351220223047, 
    "YEAR": 2011, 
    "ACCESS1": 66.951937646854, 
    "COMMUNITY_AREA": "MORGAN PARK"
  }, 
  {
    "BUSINESS_TYPE": "Animal Care Facility", 
    "ACCESS2": 55.1980375593173, 
    "YEAR": 2011, 
    "ACCESS1": 170.44233430148262, 
    "COMMUNITY_AREA": "BRIGHTON PARK"
  }, 
  {
    "BUSINESS_TYPE": "Animal Care Facility", 
    "ACCESS2": 31.773672347489164, 
    "YEAR": 2011, 
    "ACCESS1": 92.54934085656589, 
    "COMMUNITY_AREA": "MCKINLEY PARK"
  }, 
  {
    "BUSINESS_TYPE": "Animal Care Facility", 
    "ACCESS2": 14.15097836927908, 
    "YEAR": 2011, 
    "ACCESS1": 123.03146919896517, 
    "COMMUNITY_AREA": "GREATER GRAND CROSSING"
  }, 
  {
    "BUSINESS_TYPE": "Animal Care Facility", 
    "ACCESS2": 44.054738539382015, 
    "YEAR": 2011, 
    "ACCESS1": 245.44278842856832, 
    "COMMUNITY_AREA": "NEW CITY"
  }, 
  {
    "BUSINESS_TYPE": "Animal Care Facility", 
    "ACCESS2": 41.60886032908535, 
    "YEAR": 2011, 
    "ACCESS1": 54.99805349524269, 
    "COMMUNITY_AREA": "EDISON PARK"
  }, 
  {
    "BUSINESS_TYPE": "Animal Care Facility", 
    "ACCESS2": 9.769822138035938, 
    "YEAR": 2011, 
    "ACCESS1": 43.62123524882141, 
    "COMMUNITY_AREA": "OAKLAND"
  }, 
  {
    "BUSINESS_TYPE": "Animal Care Facility", 
    "ACCESS2": 119.02269075216117, 
    "YEAR": 2011, 
    "ACCESS1": 477.01875551301947, 
    "COMMUNITY_AREA": "AUSTIN"
  }, 
  {
    "BUSINESS_TYPE": "Animal Care Facility", 
    "ACCESS2": 28.362309380893453, 
    "YEAR": 2011, 
    "ACCESS1": 118.77311619640113, 
    "COMMUNITY_AREA": "GAGE PARK"
  }, 
  {
    "BUSINESS_TYPE": "Animal Care Facility", 
    "ACCESS2": 2289.1531951975744, 
    "YEAR": 2011, 
    "ACCESS1": 1571.1627171480704, 
    "COMMUNITY_AREA": "WEST TOWN"
  }
]