[
  {
    "BUSINESS_TYPE": "Single Room Occupancy Class II", 
    "ACCESS2": 1.64824398063462, 
    "YEAR": 2002, 
    "ACCESS1": 11.95475132182952, 
    "COMMUNITY_AREA": "CALUMET HEIGHTS"
  }, 
  {
    "BUSINESS_TYPE": "Single Room Occupancy Class II", 
    "ACCESS2": 464.6031363465748, 
    "YEAR": 2002, 
    "ACCESS1": 69.0105579037352, 
    "COMMUNITY_AREA": "ROGERS PARK"
  }, 
  {
    "BUSINESS_TYPE": "Single Room Occupancy Class II", 
    "ACCESS2": 16.473518364158338, 
    "YEAR": 2002, 
    "ACCESS1": 54.19327995599122, 
    "COMMUNITY_AREA": "LINCOLN SQUARE"
  }, 
  {
    "BUSINESS_TYPE": "Single Room Occupancy Class II", 
    "ACCESS2": 28.58451579453507, 
    "YEAR": 2002, 
    "ACCESS1": 79.0617489585422, 
    "COMMUNITY_AREA": "NORTH LAWNDALE"
  }, 
  {
    "BUSINESS_TYPE": "Single Room Occupancy Class II", 
    "ACCESS2": 32.46322200000328, 
    "YEAR": 2002, 
    "ACCESS1": 44.39272585852809, 
    "COMMUNITY_AREA": "ROSELAND"
  }, 
  {
    "BUSINESS_TYPE": "Single Room Occupancy Class II", 
    "ACCESS2": 6.2481428233338265, 
    "YEAR": 2002, 
    "ACCESS1": 34.685747455569505, 
    "COMMUNITY_AREA": "CHICAGO LAWN"
  }, 
  {
    "BUSINESS_TYPE": "Single Room Occupancy Class II", 
    "ACCESS2": 6.538747519433396, 
    "YEAR": 2002, 
    "ACCESS1": 40.96876884846463, 
    "COMMUNITY_AREA": "SOUTH SHORE"
  }, 
  {
    "BUSINESS_TYPE": "Single Room Occupancy Class II", 
    "ACCESS2": 15.382247341004115, 
    "YEAR": 2002, 
    "ACCESS1": 47.82436931887339, 
    "COMMUNITY_AREA": "DOUGLAS"
  }, 
  {
    "BUSINESS_TYPE": "Single Room Occupancy Class II", 
    "ACCESS2": 12.114959835842145, 
    "YEAR": 2002, 
    "ACCESS1": 41.561930022018814, 
    "COMMUNITY_AREA": "WOODLAWN"
  }, 
  {
    "BUSINESS_TYPE": "Single Room Occupancy Class II", 
    "ACCESS2": 20.62215937372675, 
    "YEAR": 2002, 
    "ACCESS1": 52.179070771351014, 
    "COMMUNITY_AREA": "HYDE PARK"
  }, 
  {
    "BUSINESS_TYPE": "Single Room Occupancy Class II", 
    "ACCESS2": 3.834722491905652, 
    "YEAR": 2002, 
    "ACCESS1": 19.37742338912362, 
    "COMMUNITY_AREA": "FOREST GLEN"
  }, 
  {
    "BUSINESS_TYPE": "Single Room Occupancy Class II", 
    "ACCESS2": 1.930537918423749, 
    "YEAR": 2002, 
    "ACCESS1": 4.8000940981631395, 
    "COMMUNITY_AREA": "HEGEWISCH"
  }, 
  {
    "BUSINESS_TYPE": "Single Room Occupancy Class II", 
    "ACCESS2": 2.8206094650097797, 
    "YEAR": 2002, 
    "ACCESS1": 22.806392803555504, 
    "COMMUNITY_AREA": "SOUTH CHICAGO"
  }, 
  {
    "BUSINESS_TYPE": "Single Room Occupancy Class II", 
    "ACCESS2": 2.84477585544457, 
    "YEAR": 2002, 
    "ACCESS1": 16.712260258806143, 
    "COMMUNITY_AREA": "ARCHER HEIGHTS"
  }, 
  {
    "BUSINESS_TYPE": "Single Room Occupancy Class II", 
    "ACCESS2": 2.173007718810976, 
    "YEAR": 2002, 
    "ACCESS1": 15.891523729871357, 
    "COMMUNITY_AREA": "BEVERLY"
  }, 
  {
    "BUSINESS_TYPE": "Single Room Occupancy Class II", 
    "ACCESS2": 36.58257987890702, 
    "YEAR": 2002, 
    "ACCESS1": 70.19294834658747, 
    "COMMUNITY_AREA": "UPTOWN"
  }, 
  {
    "BUSINESS_TYPE": "Single Room Occupancy Class II", 
    "ACCESS2": 25.30608896470935, 
    "YEAR": 2002, 
    "ACCESS1": 62.609867091717994, 
    "COMMUNITY_AREA": "AVONDALE"
  }, 
  {
    "BUSINESS_TYPE": "Single Room Occupancy Class II", 
    "ACCESS2": 0.7532833302694941, 
    "YEAR": 2002, 
    "ACCESS1": 5.151862910391795, 
    "COMMUNITY_AREA": "AVALON PARK"
  }, 
  {
    "BUSINESS_TYPE": "Single Room Occupancy Class II", 
    "ACCESS2": 0.3851735726301479, 
    "YEAR": 2002, 
    "ACCESS1": 2.5032023572637607, 
    "COMMUNITY_AREA": "BURNSIDE"
  }, 
  {
    "BUSINESS_TYPE": "Single Room Occupancy Class II", 
    "ACCESS2": 14.508435406652177, 
    "YEAR": 2002, 
    "ACCESS1": 53.656774253237565, 
    "COMMUNITY_AREA": "LOWER WEST SIDE"
  }, 
  {
    "BUSINESS_TYPE": "Single Room Occupancy Class II", 
    "ACCESS2": 18.953740921974866, 
    "YEAR": 2002, 
    "ACCESS1": 79.4687933201091, 
    "COMMUNITY_AREA": "SOUTH LAWNDALE"
  }, 
  {
    "BUSINESS_TYPE": "Single Room Occupancy Class II", 
    "ACCESS2": 7.712309334517064, 
    "YEAR": 2002, 
    "ACCESS1": 37.27032535009491, 
    "COMMUNITY_AREA": "DUNNING"
  }, 
  {
    "BUSINESS_TYPE": "Single Room Occupancy Class II", 
    "ACCESS2": 20.9881834745978, 
    "YEAR": 2002, 
    "ACCESS1": 56.440865824841175, 
    "COMMUNITY_AREA": "ALBANY PARK"
  }, 
  {
    "BUSINESS_TYPE": "Single Room Occupancy Class II", 
    "ACCESS2": 2.568917290688087, 
    "YEAR": 2002, 
    "ACCESS1": 7.9826434094948935, 
    "COMMUNITY_AREA": "PULLMAN"
  }, 
  {
    "BUSINESS_TYPE": "Single Room Occupancy Class II", 
    "ACCESS2": 9.333670272592776, 
    "YEAR": 2002, 
    "ACCESS1": 25.116176787204672, 
    "COMMUNITY_AREA": "LOOP"
  }, 
  {
    "BUSINESS_TYPE": "Single Room Occupancy Class II", 
    "ACCESS2": 15.224464702606445, 
    "YEAR": 2002, 
    "ACCESS1": 49.508033055289154, 
    "COMMUNITY_AREA": "BRIDGEPORT"
  }, 
  {
    "BUSINESS_TYPE": "Single Room Occupancy Class II", 
    "ACCESS2": 6.636040276279596, 
    "YEAR": 2002, 
    "ACCESS1": 41.72233041561168, 
    "COMMUNITY_AREA": "AUBURN GRESHAM"
  }, 
  {
    "BUSINESS_TYPE": "Single Room Occupancy Class II", 
    "ACCESS2": 803.5489285529645, 
    "YEAR": 2002, 
    "ACCESS1": 376.91367948673087, 
    "COMMUNITY_AREA": "LAKE VIEW"
  }, 
  {
    "BUSINESS_TYPE": "Single Room Occupancy Class II", 
    "ACCESS2": 76.04953854482144, 
    "YEAR": 2002, 
    "ACCESS1": 106.95740959103514, 
    "COMMUNITY_AREA": "HUMBOLDT PARK"
  }, 
  {
    "BUSINESS_TYPE": "Single Room Occupancy Class II", 
    "ACCESS2": 179.00786738362862, 
    "YEAR": 2002, 
    "ACCESS1": 94.77925991544528, 
    "COMMUNITY_AREA": "WEST GARFIELD PARK"
  }, 
  {
    "BUSINESS_TYPE": "Single Room Occupancy Class II", 
    "ACCESS2": 3.3586598655576485, 
    "YEAR": 2002, 
    "ACCESS1": 22.071188210717494, 
    "COMMUNITY_AREA": "NORWOOD PARK"
  }, 
  {
    "BUSINESS_TYPE": "Single Room Occupancy Class II", 
    "ACCESS2": 177.52217516805038, 
    "YEAR": 2002, 
    "ACCESS1": 98.80101769184127, 
    "COMMUNITY_AREA": "EAST GARFIELD PARK"
  }, 
  {
    "BUSINESS_TYPE": "Single Room Occupancy Class II", 
    "ACCESS2": 66.80817281250562, 
    "YEAR": 2002, 
    "ACCESS1": 170.095585907962, 
    "COMMUNITY_AREA": "LOGAN SQUARE"
  }, 
  {
    "BUSINESS_TYPE": "Single Room Occupancy Class II", 
    "ACCESS2": 101.34950580224354, 
    "YEAR": 2002, 
    "ACCESS1": 88.10582742486973, 
    "COMMUNITY_AREA": "PORTAGE PARK"
  }, 
  {
    "BUSINESS_TYPE": "Single Room Occupancy Class II", 
    "ACCESS2": 1.254460964123579, 
    "YEAR": 2002, 
    "ACCESS1": 8.752780434585578, 
    "COMMUNITY_AREA": "SOUTH DEERING"
  }, 
  {
    "BUSINESS_TYPE": "Single Room Occupancy Class II", 
    "ACCESS2": 73.93641454078123, 
    "YEAR": 2002, 
    "ACCESS1": 137.20027456671082, 
    "COMMUNITY_AREA": "LINCOLN PARK"
  }, 
  {
    "BUSINESS_TYPE": "Single Room Occupancy Class II", 
    "ACCESS2": 5.642406438555938, 
    "YEAR": 2002, 
    "ACCESS1": 22.343194382769454, 
    "COMMUNITY_AREA": "JEFFERSON PARK"
  }, 
  {
    "BUSINESS_TYPE": "Single Room Occupancy Class II", 
    "ACCESS2": 17.60173329736343, 
    "YEAR": 2002, 
    "ACCESS1": 69.7273801039879, 
    "COMMUNITY_AREA": "EDGEWATER"
  }, 
  {
    "BUSINESS_TYPE": "Single Room Occupancy Class II", 
    "ACCESS2": 4.3013876033030645, 
    "YEAR": 2002, 
    "ACCESS1": 26.89494107589869, 
    "COMMUNITY_AREA": "CHATHAM"
  }, 
  {
    "BUSINESS_TYPE": "Single Room Occupancy Class II", 
    "ACCESS2": 2.354831517133162, 
    "YEAR": 2002, 
    "ACCESS1": 16.67307303288157, 
    "COMMUNITY_AREA": "WEST LAWN"
  }, 
  {
    "BUSINESS_TYPE": "Single Room Occupancy Class II", 
    "ACCESS2": 13.151210929405686, 
    "YEAR": 2002, 
    "ACCESS1": 52.26857631354126, 
    "COMMUNITY_AREA": "WEST RIDGE"
  }, 
  {
    "BUSINESS_TYPE": "Single Room Occupancy Class II", 
    "ACCESS2": 72.76590077385983, 
    "YEAR": 2002, 
    "ACCESS1": 120.3445420870801, 
    "COMMUNITY_AREA": "NEAR WEST SIDE"
  }, 
  {
    "BUSINESS_TYPE": "Single Room Occupancy Class II", 
    "ACCESS2": 15.482756190221943, 
    "YEAR": 2002, 
    "ACCESS1": 46.044393381527335, 
    "COMMUNITY_AREA": "ENGLEWOOD"
  }, 
  {
    "BUSINESS_TYPE": "Single Room Occupancy Class II", 
    "ACCESS2": 98.60076495067976, 
    "YEAR": 2002, 
    "ACCESS1": 111.3411010970657, 
    "COMMUNITY_AREA": "NORTH CENTER"
  }, 
  {
    "BUSINESS_TYPE": "Single Room Occupancy Class II", 
    "ACCESS2": 42.856366598409366, 
    "YEAR": 2002, 
    "ACCESS1": 38.999414086055154, 
    "COMMUNITY_AREA": "WASHINGTON PARK"
  }, 
  {
    "BUSINESS_TYPE": "Single Room Occupancy Class II", 
    "ACCESS2": 3.2879899338033276, 
    "YEAR": 2002, 
    "ACCESS1": 13.199500687188857, 
    "COMMUNITY_AREA": "NEAR SOUTH SIDE"
  }, 
  {
    "BUSINESS_TYPE": "Single Room Occupancy Class II", 
    "ACCESS2": 1.9581273223959108, 
    "YEAR": 2002, 
    "ACCESS1": 18.562482935506345, 
    "COMMUNITY_AREA": "OHARE"
  }, 
  {
    "BUSINESS_TYPE": "Single Room Occupancy Class II", 
    "ACCESS2": 6.139304499526248, 
    "YEAR": 2002, 
    "ACCESS1": 19.225082784635198, 
    "COMMUNITY_AREA": "WEST PULLMAN"
  }, 
  {
    "BUSINESS_TYPE": "Single Room Occupancy Class II", 
    "ACCESS2": 170.87573282677712, 
    "YEAR": 2002, 
    "ACCESS1": 135.86412944426257, 
    "COMMUNITY_AREA": "NEAR NORTH SIDE"
  }, 
  {
    "BUSINESS_TYPE": "Single Room Occupancy Class II", 
    "ACCESS2": 0.7916211883680715, 
    "YEAR": 2002, 
    "ACCESS1": 7.769289389819223, 
    "COMMUNITY_AREA": "MOUNT GREENWOOD"
  }, 
  {
    "BUSINESS_TYPE": "Single Room Occupancy Class II", 
    "ACCESS2": 17.51184883712888, 
    "YEAR": 2002, 
    "ACCESS1": 16.391572609319702, 
    "COMMUNITY_AREA": "FULLER PARK"
  }, 
  {
    "BUSINESS_TYPE": "Single Room Occupancy Class II", 
    "ACCESS2": 1.5442624725786263, 
    "YEAR": 2002, 
    "ACCESS1": 7.336599323723929, 
    "COMMUNITY_AREA": "MONTCLARE"
  }, 
  {
    "BUSINESS_TYPE": "Single Room Occupancy Class II", 
    "ACCESS2": 85.99767975631869, 
    "YEAR": 2002, 
    "ACCESS1": 102.435821279244, 
    "COMMUNITY_AREA": "IRVING PARK"
  }, 
  {
    "BUSINESS_TYPE": "Single Room Occupancy Class II", 
    "ACCESS2": 23735.22629854684, 
    "YEAR": 2002, 
    "ACCESS1": 295.071106815434, 
    "COMMUNITY_AREA": "GRAND BOULEVARD"
  }, 
  {
    "BUSINESS_TYPE": "Single Room Occupancy Class II", 
    "ACCESS2": 0.7670045791945812, 
    "YEAR": 2002, 
    "ACCESS1": 4.159150545029868, 
    "COMMUNITY_AREA": "RIVERDALE"
  }, 
  {
    "BUSINESS_TYPE": "Single Room Occupancy Class II", 
    "ACCESS2": 21.92828006206299, 
    "YEAR": 2002, 
    "ACCESS1": 39.668130605097666, 
    "COMMUNITY_AREA": "HERMOSA"
  }, 
  {
    "BUSINESS_TYPE": "Single Room Occupancy Class II", 
    "ACCESS2": 3.965873508412045, 
    "YEAR": 2002, 
    "ACCESS1": 16.261111025919277, 
    "COMMUNITY_AREA": "NORTH PARK"
  }, 
  {
    "BUSINESS_TYPE": "Single Room Occupancy Class II", 
    "ACCESS2": 50.67383062938912, 
    "YEAR": 2002, 
    "ACCESS1": 94.00896039797034, 
    "COMMUNITY_AREA": "BELMONT CRAGIN"
  }, 
  {
    "BUSINESS_TYPE": "Single Room Occupancy Class II", 
    "ACCESS2": 7.4772158165895, 
    "YEAR": 2002, 
    "ACCESS1": 24.368633506531744, 
    "COMMUNITY_AREA": "ARMOUR SQUARE"
  }, 
  {
    "BUSINESS_TYPE": "Single Room Occupancy Class II", 
    "ACCESS2": 20.16242893916173, 
    "YEAR": 2002, 
    "ACCESS1": 72.92024745114749, 
    "COMMUNITY_AREA": "WEST ENGLEWOOD"
  }, 
  {
    "BUSINESS_TYPE": "Single Room Occupancy Class II", 
    "ACCESS2": 15.947987485317789, 
    "YEAR": 2002, 
    "ACCESS1": 34.195284639206754, 
    "COMMUNITY_AREA": "KENWOOD"
  }, 
  {
    "BUSINESS_TYPE": "Single Room Occupancy Class II", 
    "ACCESS2": 2.019384604390692, 
    "YEAR": 2002, 
    "ACCESS1": 17.213958911916478, 
    "COMMUNITY_AREA": "CLEARING"
  }, 
  {
    "BUSINESS_TYPE": "Single Room Occupancy Class II", 
    "ACCESS2": 3.6380348530728153, 
    "YEAR": 2002, 
    "ACCESS1": 20.296302468144656, 
    "COMMUNITY_AREA": "WASHINGTON HEIGHTS"
  }, 
  {
    "BUSINESS_TYPE": "Single Room Occupancy Class II", 
    "ACCESS2": 1.463251371104456, 
    "YEAR": 2002, 
    "ACCESS1": 11.921729810848626, 
    "COMMUNITY_AREA": "EAST SIDE"
  }, 
  {
    "BUSINESS_TYPE": "Single Room Occupancy Class II", 
    "ACCESS2": 4.145056071636659, 
    "YEAR": 2002, 
    "ACCESS1": 30.649170139303507, 
    "COMMUNITY_AREA": "GARFIELD RIDGE"
  }, 
  {
    "BUSINESS_TYPE": "Single Room Occupancy Class II", 
    "ACCESS2": 2.45038948917022, 
    "YEAR": 2002, 
    "ACCESS1": 19.606564570912, 
    "COMMUNITY_AREA": "ASHBURN"
  }, 
  {
    "BUSINESS_TYPE": "Single Room Occupancy Class II", 
    "ACCESS2": 2.004850481962608, 
    "YEAR": 2002, 
    "ACCESS1": 12.471461253791485, 
    "COMMUNITY_AREA": "WEST ELSDON"
  }, 
  {
    "BUSINESS_TYPE": "Single Room Occupancy Class II", 
    "ACCESS2": 2.504722397258743, 
    "YEAR": 2002, 
    "ACCESS1": 15.072075193178593, 
    "COMMUNITY_AREA": "MORGAN PARK"
  }, 
  {
    "BUSINESS_TYPE": "Single Room Occupancy Class II", 
    "ACCESS2": 10.572680651276858, 
    "YEAR": 2002, 
    "ACCESS1": 41.70731207083407, 
    "COMMUNITY_AREA": "BRIGHTON PARK"
  }, 
  {
    "BUSINESS_TYPE": "Single Room Occupancy Class II", 
    "ACCESS2": 7.5966066035910345, 
    "YEAR": 2002, 
    "ACCESS1": 24.202551549698814, 
    "COMMUNITY_AREA": "MCKINLEY PARK"
  }, 
  {
    "BUSINESS_TYPE": "Single Room Occupancy Class II", 
    "ACCESS2": 8.605604678978299, 
    "YEAR": 2002, 
    "ACCESS1": 39.453772823461286, 
    "COMMUNITY_AREA": "GREATER GRAND CROSSING"
  }, 
  {
    "BUSINESS_TYPE": "Single Room Occupancy Class II", 
    "ACCESS2": 121.09892128970428, 
    "YEAR": 2002, 
    "ACCESS1": 113.0870336063883, 
    "COMMUNITY_AREA": "NEW CITY"
  }, 
  {
    "BUSINESS_TYPE": "Single Room Occupancy Class II", 
    "ACCESS2": 1.072722962878565, 
    "YEAR": 2002, 
    "ACCESS1": 9.175896204965355, 
    "COMMUNITY_AREA": "EDISON PARK"
  }, 
  {
    "BUSINESS_TYPE": "Single Room Occupancy Class II", 
    "ACCESS2": 4.469854941108885, 
    "YEAR": 2002, 
    "ACCESS1": 13.591195884669272, 
    "COMMUNITY_AREA": "OAKLAND"
  }, 
  {
    "BUSINESS_TYPE": "Single Room Occupancy Class II", 
    "ACCESS2": 104.39130388320389, 
    "YEAR": 2002, 
    "ACCESS1": 147.95101597337037, 
    "COMMUNITY_AREA": "AUSTIN"
  }, 
  {
    "BUSINESS_TYPE": "Single Room Occupancy Class II", 
    "ACCESS2": 7.622901161269627, 
    "YEAR": 2002, 
    "ACCESS1": 30.350043472430716, 
    "COMMUNITY_AREA": "GAGE PARK"
  }, 
  {
    "BUSINESS_TYPE": "Single Room Occupancy Class II", 
    "ACCESS2": 61.32748582493555, 
    "YEAR": 2002, 
    "ACCESS1": 183.84356347494398, 
    "COMMUNITY_AREA": "WEST TOWN"
  }
]