[
  {
    "BUSINESS_TYPE": "Special Event Food", 
    "LEGAL_NAME": "THE CATHOLIC CHARITIES OF THE ARCHDIOCESE OF CHICAGO", 
    "STATE": "IL", 
    "DOING_BUSINESS_AS_NAME": "St. Michael School", 
    "POP_AT_RISK": 33876, 
    "ZIP": 60617, 
    "ADDRESS": "8235 S SOUTH SHORE DR", 
    "YEAR": 2009, 
    "LONGITUDE": -87.54777337, 
    "LATTITUDE": 41.745474809
  }, 
  {
    "BUSINESS_TYPE": "Special Event Food", 
    "LEGAL_NAME": "To Tu Cafe Corporation", 
    "STATE": "IL", 
    "DOING_BUSINESS_AS_NAME": "TO TU CAFE", 
    "POP_AT_RISK": 14869, 
    "ZIP": 60646, 
    "ADDRESS": "6100 N CICERO AVE", 
    "YEAR": 2009, 
    "LONGITUDE": -87.748475228, 
    "LATTITUDE": 41.991483828
  }, 
  {
    "BUSINESS_TYPE": "Special Event Food", 
    "LEGAL_NAME": "LENDERA COLLINS", 
    "STATE": "IL", 
    "DOING_BUSINESS_AS_NAME": "MORNING GLORY", 
    "POP_AT_RISK": 38714, 
    "ZIP": 60653, 
    "ADDRESS": "4433 S ST LAWRENCE AVE", 
    "YEAR": 2009, 
    "LONGITUDE": -87.611417903, 
    "LATTITUDE": 41.813905144
  }, 
  {
    "BUSINESS_TYPE": "Special Event Food", 
    "LEGAL_NAME": "STEVE AGOU", 
    "STATE": "IL", 
    "DOING_BUSINESS_AS_NAME": "ASSUMPTION CHURCH", 
    "POP_AT_RISK": 25175, 
    "ZIP": 60644, 
    "ADDRESS": "601 S CENTRAL AVE", 
    "YEAR": 2009, 
    "LONGITUDE": -87.7644383, 
    "LATTITUDE": 41.87277985
  }, 
  {
    "BUSINESS_TYPE": "Special Event Food", 
    "LEGAL_NAME": "BLUE PLATE CATERING LTD.", 
    "STATE": "IL", 
    "DOING_BUSINESS_AS_NAME": "BLUE PLATE CATERING LTD", 
    "POP_AT_RISK": 33058, 
    "ZIP": 60631, 
    "ADDRESS": "5624 N NEWARK AVE", 
    "YEAR": 2009, 
    "LONGITUDE": -87.795228429, 
    "LATTITUDE": 41.983639018
  }, 
  {
    "BUSINESS_TYPE": "Special Event Food", 
    "LEGAL_NAME": "ST HELEN SCHOOL", 
    "STATE": "IL", 
    "DOING_BUSINESS_AS_NAME": "ST HELEN SCHOOL", 
    "POP_AT_RISK": 56961, 
    "ZIP": 60622, 
    "ADDRESS": "2347 W AUGUSTA BLVD", 
    "YEAR": 2009, 
    "LONGITUDE": -87.686355067, 
    "LATTITUDE": 41.899278248
  }, 
  {
    "BUSINESS_TYPE": "Special Event Food", 
    "LEGAL_NAME": "CATHOLIC BISHOP OF CHICAGO", 
    "STATE": "IL", 
    "DOING_BUSINESS_AS_NAME": "OUR LADY OF GUADALUPE PARISH", 
    "POP_AT_RISK": 17702, 
    "ZIP": 60617, 
    "ADDRESS": "3216 E 91ST ST", 
    "YEAR": 2009, 
    "LONGITUDE": -87.54617084, 
    "LATTITUDE": 41.730243534
  }, 
  {
    "BUSINESS_TYPE": "Special Event Food", 
    "LEGAL_NAME": "CIRCLE FAMILY HEALTHCARE NETWORK, INC.", 
    "STATE": "IL", 
    "DOING_BUSINESS_AS_NAME": "ROCK CHURCH/CIRCLE URBAN MINISTRIES", 
    "POP_AT_RISK": 39739, 
    "ZIP": 60644, 
    "ADDRESS": "118 N CENTRAL AVE", 
    "YEAR": 2009, 
    "LONGITUDE": -87.765095452, 
    "LATTITUDE": 41.882845075
  }, 
  {
    "BUSINESS_TYPE": "Special Event Food", 
    "LEGAL_NAME": "PODRUMEDIC RESTAURANTS, INC.", 
    "STATE": "IL", 
    "DOING_BUSINESS_AS_NAME": "BUCHAREST CONTINENTAL CAFE", 
    "POP_AT_RISK": 61589, 
    "ZIP": 60618, 
    "ADDRESS": "3400 N CALIFORNIA AVE", 
    "YEAR": 2009, 
    "LONGITUDE": -87.698072336, 
    "LATTITUDE": 41.9428947
  }, 
  {
    "BUSINESS_TYPE": "Special Event Food", 
    "LEGAL_NAME": "ORIGINAL RAINBOW CONE, INC.", 
    "STATE": "IL", 
    "DOING_BUSINESS_AS_NAME": "ORIGINAL RAINBOW CONE", 
    "POP_AT_RISK": 16844, 
    "ZIP": 60643, 
    "ADDRESS": "10650 S LONGWOOD DR", 
    "YEAR": 2009, 
    "LONGITUDE": -87.671251081, 
    "LATTITUDE": 41.699537213
  }, 
  {
    "BUSINESS_TYPE": "Special Event Food", 
    "LEGAL_NAME": "ORIGINAL RAINBOW CONE, INC.", 
    "STATE": "IL", 
    "DOING_BUSINESS_AS_NAME": "ORIGINAL RAINBOW CONE", 
    "POP_AT_RISK": 19607, 
    "ZIP": 60643, 
    "ADDRESS": "2153 W 111TH ST", 
    "YEAR": 2009, 
    "LONGITUDE": -87.676008619, 
    "LATTITUDE": 41.691747004
  }, 
  {
    "BUSINESS_TYPE": "Special Event Food", 
    "LEGAL_NAME": "TROY  M  JOHNSON", 
    "STATE": "IL", 
    "DOING_BUSINESS_AS_NAME": "Ms. Minnie's Soul Food Cafe", 
    "POP_AT_RISK": 39745, 
    "ZIP": 60649, 
    "ADDRESS": "7827 S STONY ISLAND AVE", 
    "YEAR": 2009, 
    "LONGITUDE": -87.585337857, 
    "LATTITUDE": 41.752474748
  }, 
  {
    "BUSINESS_TYPE": "Special Event Food", 
    "LEGAL_NAME": "MATERNITY B.V.M. CHURCH", 
    "STATE": "IL", 
    "DOING_BUSINESS_AS_NAME": "MATERNITY B.V.M. CHURCH", 
    "POP_AT_RISK": 73007, 
    "ZIP": 60647, 
    "ADDRESS": "3647 W NORTH AVE", 
    "YEAR": 2009, 
    "LONGITUDE": -87.718636249, 
    "LATTITUDE": 41.909860488
  }, 
  {
    "BUSINESS_TYPE": "Special Event Food", 
    "LEGAL_NAME": "FREDDIE'S INC.", 
    "STATE": "IL", 
    "DOING_BUSINESS_AS_NAME": "FREDDIE'S RESTAURANT", 
    "POP_AT_RISK": 36167, 
    "ZIP": 60616, 
    "ADDRESS": "2800 S PRINCETON AVE", 
    "YEAR": 2009, 
    "LONGITUDE": -87.634358826, 
    "LATTITUDE": 41.842511199
  }, 
  {
    "BUSINESS_TYPE": "Special Event Food", 
    "LEGAL_NAME": "Kent Chase", 
    "STATE": "IL", 
    "DOING_BUSINESS_AS_NAME": "CHASE EVENTS", 
    "POP_AT_RISK": 67240, 
    "ZIP": 60640, 
    "ADDRESS": "931 W EASTWOOD AVE", 
    "YEAR": 2009, 
    "LONGITUDE": -87.653913236, 
    "LATTITUDE": 41.9662767
  }, 
  {
    "BUSINESS_TYPE": "Special Event Food", 
    "LEGAL_NAME": "OUR LADY MOTHER OF THE CHURCH", 
    "STATE": "IL", 
    "DOING_BUSINESS_AS_NAME": "Our Lady, Mother of the Church", 
    "POP_AT_RISK": 12033, 
    "ZIP": 60656, 
    "ADDRESS": "8747 W LAWRENCE AVE", 
    "YEAR": 2009, 
    "LONGITUDE": -87.845584144, 
    "LATTITUDE": 41.966321788
  }, 
  {
    "BUSINESS_TYPE": "Special Event Food", 
    "LEGAL_NAME": "ST. PANCRATIUS", 
    "STATE": "IL", 
    "DOING_BUSINESS_AS_NAME": "St. Pancratius", 
    "POP_AT_RISK": 44045, 
    "ZIP": 60632, 
    "ADDRESS": "2930 W 40TH PL", 
    "YEAR": 2009, 
    "LONGITUDE": -87.698265715, 
    "LATTITUDE": 41.820128714
  }, 
  {
    "BUSINESS_TYPE": "Special Event Food", 
    "LEGAL_NAME": "Southside Community Outreach Coalition", 
    "STATE": "IL", 
    "DOING_BUSINESS_AS_NAME": "MOO & ONIK", 
    "POP_AT_RISK": 34307, 
    "ZIP": 60621, 
    "ADDRESS": "6700 S HALSTED ST", 
    "YEAR": 2009, 
    "LONGITUDE": -87.644741642, 
    "LATTITUDE": 41.772379617
  }, 
  {
    "BUSINESS_TYPE": "Special Event Food", 
    "LEGAL_NAME": "Schmeisser Meats & Sausage, Inc.", 
    "STATE": "IL", 
    "DOING_BUSINESS_AS_NAME": "SCHMEISSER'S", 
    "POP_AT_RISK": 55730, 
    "ZIP": 60609, 
    "ADDRESS": "4700 S WESTERN AVE", 
    "YEAR": 2009, 
    "LONGITUDE": -87.684570717, 
    "LATTITUDE": 41.808378408
  }, 
  {
    "BUSINESS_TYPE": "Special Event Food", 
    "LEGAL_NAME": "St. Ferdinand Church", 
    "STATE": "IL", 
    "DOING_BUSINESS_AS_NAME": "ST. FERDINAND CHURCH", 
    "POP_AT_RISK": 54111, 
    "ZIP": 60634, 
    "ADDRESS": "3141 N MASON AVE", 
    "YEAR": 2009, 
    "LONGITUDE": -87.77483259, 
    "LATTITUDE": 41.937865517
  }, 
  {
    "BUSINESS_TYPE": "Special Event Food", 
    "LEGAL_NAME": "ST DEMETRIOS GREEK ORTHODOX CH", 
    "STATE": "IL", 
    "DOING_BUSINESS_AS_NAME": "CHICAGO'S GREEFEST", 
    "POP_AT_RISK": 62086, 
    "ZIP": 60625, 
    "ADDRESS": "2727 W WINONA ST", 
    "YEAR": 2009, 
    "LONGITUDE": -87.697529457, 
    "LATTITUDE": 41.974653353
  }, 
  {
    "BUSINESS_TYPE": "Special Event Food", 
    "LEGAL_NAME": "ARCHBISHOP OF CHICAGO", 
    "STATE": "IL", 
    "DOING_BUSINESS_AS_NAME": "ST GABRIEL (BOOTHS 1&2)", 
    "POP_AT_RISK": 15216, 
    "ZIP": 60609, 
    "ADDRESS": "600 W 45TH ST", 
    "YEAR": 2009, 
    "LONGITUDE": -87.640836037, 
    "LATTITUDE": 41.8127186
  }, 
  {
    "BUSINESS_TYPE": "Special Event Food", 
    "LEGAL_NAME": "LEVY PREMIUM FOODSERVICE LIMITED PARTNERSHIP", 
    "STATE": "IL", 
    "DOING_BUSINESS_AS_NAME": "Levy Premium Food Service LP Booths 1, 2 & 3", 
    "POP_AT_RISK": 38652, 
    "ZIP": 60612, 
    "ADDRESS": "1901 W MADISON ST", 
    "YEAR": 2009, 
    "LONGITUDE": -87.674282534, 
    "LATTITUDE": 41.881241457
  }
]